{
 "BatJosh":{"Rank":"WorldDev", "Privilege":"Staff"},
 
 "crybunni":{"Rank:"Owner", "Privilege":"Staff"},
 
 "OpheliaლPrime":{"Rank":"Management", "Privilege":"Staff"},
 "jellylicious":{"Rank":"Management", "Privilege":"Staff"},
 "Royal Bubble":{"Rank":"Management", "Privilege":"Staff"},
 "Αmelio":{"Rank":"Management", "Privilege":"Staff"},
 
 "absiske":{"Rank":"LeadDancer", "Privilege":"Staff"},
 
 "spektrr":{"Rank":"Photographers", "Privilege":"Staff"},
 "M3k_A":{"Rank":"Photographers", "Privilege":"Staff"},
 "NoireVR":{"Rank":"Photographers", "Privilege":"Staff"},
 "Miss_Vixen":{"Rank":"Photographers", "Privilege":"Staff"},
 "Ｊｏｏｎｉ３":{"Rank":"Photographers", "Privilege":"Staff"},
 
 "bewitchedvr":{"Rank":"Security", "Privilege":"Staff"},
 "GazHazMaz":{"Rank":"Security", "Privilege":"Staff"},
 "Zakattak":{"Rank":"Security", "Privilege":"Staff"},
 "Sneck96":{"Rank":"Security", "Privilege":"Staff"},
 "Sminky Grandpa":{"Rank":"Security", "Privilege":"Staff"},
 "TinyBrainPlays":{"Rank":"Security", "Privilege":"Staff"},
 "Pennylicious":{"Rank":"Security", "Privilege":"Staff"},
 "Bitzii":{"Rank":"Security", "Privilege":"Staff"},
 "zMKariusz":{"Rank":"Security", "Privilege":"Staff"},
 "cthulahoop":{"Rank":"Security", "Privilege":"Staff"},
 "CrimsonRose199":{"Rank":"Security", "Privilege":"Staff"},
 
 "emilaybaybee":{"Rank":"Host", "Privilege":"Staff"},
 "Moo Moos":{"Rank":"Host", "Privilege":"Staff"},
 "MysticCooKi3":{"Rank":"Host", "Privilege":"Staff"},
 "₩єight":{"Rank":"Host", "Privilege":"Staff"},
 "~K․a․i~":{"Rank":"Host", "Privilege":"Staff"},
 "DukeofMayonaise":{"Rank":"Host", "Privilege":"Staff"},
 "Dr Fate":{"Rank":"Host", "Privilege":"Staff"},
 "AllForNothin":{"Rank":"Host", "Privilege":"Staff"},
 "~ Kaiko ~":{"Rank":"Host", "Privilege":"Staff"},
 "Legorian":{"Rank":"Host", "Privilege":"Staff"},
 
 "RGRDrangon":{"Rank":"DJ", "Privilege":"Staff"},
 "maxxmask":{"Rank":"DJ", "Privilege":"Staff"},
 "ArcSlayerVR":{"Rank":"DJ", "Privilege":"Staff"},
 "ILoveKittens554":{"Rank":"DJ", "Privilege":"Staff"},
 
 "-Anks-":{"Rank":"Dancer", "Privilege":"Staff"},
 "~Lustful Lovie~":{"Rank":"Dancer", "Privilege":"Staff"},
 "JellyBayBee":{"Rank":"Dancer", "Privilege":"Staff"},
 "ɳ ʝ ɳ α":{"Rank":"Dancer", "Privilege":"Staff"},
 "Queenie25":{"Rank":"Dancer", "Privilege":"Staff"},
 "seakaii":{"Rank":"Dancer", "Privilege":"Staff"},
 "SayxriSakura":{"Rank":"Dancer", "Privilege":"Staff"},
 "SYUndead":{"Rank":"Dancer", "Privilege":"Staff"},
 "CookieCrvmb":{"Rank":"Dancer", "Privilege":"Staff"},
 "ＫＡＮＤＹＴＯ":{"Rank":"Dancer", "Privilege":"Staff"},
 "ToughCookies":{"Rank":"Dancer", "Privilege":"Staff"},
 "LittleJodie":{"Rank":"Dancer", "Privilege":"Staff"},
 "ღ xMylki ღ":{"Rank":"Dancer", "Privilege":"Staff"},
 "Lilith???":{"Rank":"Dancer", "Privilege":"Staff"},
 "Ironically_Ace":{"Rank":"Dancer", "Privilege":"Staff"},
 "Sireede":{"Rank":"Dancer", "Privilege":"Staff"},
 "ৎ୭Kittenৎ୭":{"Rank":"Dancer", "Privilege":"Staff"},
 "Rose_Blue_Panda":{"Rank":"Dancer", "Privilege":"Staff"},

 "Lµmï~":{"Rank":"DancerTrial", "Privilege":"Staff"},
 "moesicle":{"Rank":"DancerTrial", "Privilege":"Staff"},
 "SecuredWolf101":{"Rank":"DancerTrial", "Privilege":"Staff"},
 "Hunnieebunny":{"Rank":"DancerTrial", "Privilege":"Staff"},
 "rinuchka":{"Rank":"DancerTrial", "Privilege":"Staff"},
 "onyx°³°":{"Rank":"DancerTrial", "Privilege":"Staff"},
 "Lady Julu":{"Rank":"DancerTrial", "Privilege":"Staff"},
 "Lady۵Kallari":{"Rank":"DancerTrial", "Privilege":"Staff"},
 "Ashtrid":{"Rank":"DancerTrial", "Privilege":"Staff"},
 "BlairVRX":{"Rank":"DancerTrial", "Privilege":"Staff"},
 "Little_Kiko":{"Rank":"DancerTrial", "Privilege":"Staff"},
 "SuckMyPickle36":{"Rank":"DancerTrial", "Privilege":"Staff"},
 "CherryBlade":{"Rank":"DancerTrial", "Privilege":"Staff"},
 "-Lola Bunny-":{"Rank":"DancerTrial", "Privilege":"Staff"},
 "CherryBlade":{"Rank":"DancerTrial", "Privilege":"Staff"},
}
