{
  "WorldSettings": {
    "Colour": "5000FC"
  },
  "BatJosh": {
    "Rank": "WorldDev",
    "Privilege": "Staff"
  },
  "crybunni": {
    "Rank": "Owner",
    "Privilege": "Staff"
  },
  "bewitchedvr": {
    "Rank": "Security",
    "Privilege": "Staff"
  },
  "Zakattak": {
    "Rank": "Security",
    "Privilege": "Staff"
  },
  "Moo Moos": {
    "Rank": "Host",
    "Privilege": "Staff"
  },
  "MysticCooKi3": {
    "Rank": "Host",
    "Privilege": "Staff"
  },
  "₩єight": {
    "Rank": "Host",
    "Privilege": "Staff"
  },
  "AllForNothin": {
    "Rank": "Host",
    "Privilege": "Staff"
  },
  "ILoveKittens554": {
    "Rank": "DJ",
    "Privilege": "Staff"
  },
  "JellyBayBee": {
    "Rank": "Dancer",
    "Privilege": "Staff"
  },
  "Queenie25": {
    "Rank": "Dancer",
    "Privilege": "Staff"
  },
  "LittleJodie": {
    "Rank": "Dancer",
    "Privilege": "Staff"
  },
  "ღ xMylki ღ": {
    "Rank": "Dancer",
    "Privilege": "Staff"
  },
  "Leon Dragonwolf": {
    "Rank": "Patreon",
    "Privilege": "VVIP"
  },
  "KILLERSensei": {
    "Rank": "Booster",
    "Privilege": "VVIP"
  },
  "zeeep": {
    "Rank": "Booster",
    "Privilege": "VVIP"
  },
  "-Oaktree-": {
    "Rank": "Partners",
    "Privilege": "VVIP"
  },
  "Itz Soph": {
    "Rank": "Partners",
    "Privilege": "VVIP"
  },
  "Soap23": {
    "Rank": "Partners",
    "Privilege": "VVIP"
  },
  "DavidCrimSnake": {
    "Rank": "Security",
    "Privilege": "Staff"
  },
  "Rosa_Blue_Panda": {
    "Rank": "Dancer",
    "Privilege": "Staff"
  },
  "stihl": {
    "Rank": "Patreon",
    "Privilege": "VVIP"
  },
  "Milky_Mayngo": {
    "Rank": "DancerTrial",
    "Privilege": "Staff"
  },
  "TinyAlison": {
    "Rank": "Patreon",
    "Privilege": "VVIP"
  },
  "-Anks-": {
    "Rank": "DJ",
    "Privilege": "Staff"
  },
  "ღ Queentastic ღ": {
    "Rank": "DJ",
    "Privilege": "Staff"
  },
  "emilaybaybee": {
    "Rank": "Management",
    "Privilege": "Staff",
    "BdayStaff": "True"
  },
  "MüsïcLüv": {
    "Rank": "Booster",
    "Privilege": "VVIP"
  },
  "Jean D'Nim": {
    "Rank": "Dancer",
    "Privilege": "Staff"
  },
  "Ralaigon": {
    "Rank": "Booster",
    "Privilege": "VVIP"
  },
  "nebulous being": {
    "Rank": "Dancer",
    "Privilege": "Staff"
  },
  "Kazan-": {
    "Rank": "Booster",
    "Privilege": "VVIP"
  },
  "Mikadow": {
    "Rank": "Dancer",
    "Privilege": "Staff"
  },
  "LexiWolf727": {
    "Rank": "Booster",
    "Privilege": "VVIP"
  },
  "VoidEternal": {
    "Rank": "DancerTrial",
    "Privilege": "Staff"
  },
  "sovereigndragon": {
    "Rank": "Booster",
    "Privilege": "VVIP"
  },
  "B-lockdown": {
    "Rank": "Booster",
    "Privilege": "VVIP"
  },
  "ChensōManチェーンソー": {
    "Rank": "Host",
    "Privilege": "Staff"
  },
  "Legorian": {
    "Rank": "Host",
    "Privilege": "Staff"
  },
  "Hex Bubble": {
    "Rank": "Management",
    "Privilege": "Staff",
    "BdayStaff": "True"
  },
  "Sweep Meep": {
    "Rank": "Booster",
    "Privilege": "VVIP"
  },
  "＋XRikaღKittyX＋": {
    "Rank": "Dancer",
    "Privilege": "Staff"
  },
  "❤️Star❤️": {
    "Rank": "Management",
    "Privilege": "Staff",
    "BdayStaff": "True"
  },
  "Nex ツ": {
    "Rank": "LeadDancer",
    "Privilege": "Staff"
  },
  "absiske": {
    "Rank": "DancerTrial",
    "Privilege": "Staff"
  },
  "DakotaVosselman": {
    "Rank": "Dancer",
    "Privilege": "Staff"
  },
  "OpheliaლPrime": {
    "Rank": "Host",
    "Privilege": "Staff"
  },
  "subparstripper": {
    "Rank": "Patreon",
    "Privilege": "VVIP"
  },
  "_Angelus_": {
    "Rank": "Booster",
    "Privilege": "VVIP"
  },
  "Jaegerweeb": {
    "Rank": "Booster",
    "Privilege": "VVIP"
  },
  "Prism_Shift": {
    "Rank": "Booster",
    "Privilege": "VVIP"
  },
  "Grindbox": {
    "Rank": "Booster",
    "Privilege": "VVIP"
  },
  "Milfhunter69≺3": {
    "Rank": "Photographers",
    "Privilege": "Staff"
  },
  "T0t0r090": {
    "Rank": "DancerTrial",
    "Privilege": "Staff"
  },
  "MLGPopcorn": {
    "Rank": "Photographers",
    "Privilege": "Staff"
  },
  "Yögi": {
    "Rank": "Booster",
    "Privilege": "VVIP"
  },
  "ahnuheekireeki": {
    "Rank": "Booster",
    "Privilege": "VVIP"
  },
  "welldooder64": {
    "Rank": "Booster",
    "Privilege": "VVIP"
  },
  "Luckynmb13": {
    "Rank": "Booster",
    "Privilege": "VVIP"
  },
  "ʚ ѕɪєкσ ɞ": {
    "Rank": "Booster",
    "Privilege": "VVIP"
  },
  "П I П Λ": {
    "Rank": "Dancer",
    "Privilege": "Staff"
  },
  "JRSHACK": {
    "Rank": "Booster",
    "Privilege": "VVIP"
  },
  "RenkinFOX＄": {
    "Rank": "Booster",
    "Privilege": "VVIP"
  },
  "Bootleg Sid": {
    "Rank": "Patreon",
    "Privilege": "VVIP"
  },
  "DarthBillBo": {
    "Rank": "Booster",
    "Privilege": "VVIP"
  },
  "Flex___": {
    "Rank": "Booster",
    "Privilege": "VVIP"
  },
  "Sharkie the pan": {
    "Rank": "DancerTrial",
    "Privilege": "Staff"
  },
  "Hacabro": {
    "Rank": "Photographers",
    "Privilege": "Staff"
  },
  "Sweet Caramel": {
    "Rank": "Photographers",
    "Privilege": "Staff"
  },
  "『ᴋᴏᴡᴍᴀᴘ』": {
    "Rank": "Booster",
    "Privilege": "VVIP"
  },
  "LunaMothy": {
    "Rank": "Dancer",
    "Privilege": "Staff"
  },
  "Kreya": {
    "Rank": "Dancer",
    "Privilege": "Staff"
  },
  "onyx°³°": {
    "Rank": "Dancer",
    "Privilege": "Staff"
  },
  "Taliyuh": {
    "Rank": "Booster",
    "Privilege": "VVIP"
  },
  "PandemoniumLord": {
    "Rank": "Booster",
    "Privilege": "VVIP"
  },
  "Asher_2": {
    "Rank": "Dancer",
    "Privilege": "Staff"
  },
  "Raptor03": {
    "Rank": "Booster",
    "Privilege": "VVIP"
  },
  "ღ_RoyalWolf_ღ": {
    "Rank": "DancerTrial",
    "Privilege": "Staff"
  },
  "ღ_yuki_ღ": {
    "Rank": "DancerTrial",
    "Privilege": "Staff"
  },
  "Newf": {
    "Rank": "Photographers",
    "Privilege": "Staff"
  },
  "ʙᴏᴏᴛʏʟɪᴄɪᴏᴜs": {
    "Rank": "Patreon",
    "Privilege": "VVIP"
  },
  "CitarNosis": {
    "Rank": "Patreon",
    "Privilege": "VVIP"
  },
  "Shock7689": {
    "Rank": "Booster",
    "Privilege": "VVIP"
  },
  "ღ_lia_ღ": {
    "Rank": "Dancer",
    "Privilege": "Staff"
  },
  "DaisyDays": {
    "Rank": "LeadDancer",
    "Privilege": "Staff"
  },
  "ᴳʳᵉʸ": {
    "Rank": "Host",
    "Privilege": "Staff"
  },
  "tinyalison": {
    "Rank": "Patreon",
    "Privilege": "VVIP"
  },
  "easiexd": {
    "Rank": "Patreon",
    "Privilege": "VVIP"
  },
  "GreemVex": {
    "Rank": "Booster",
    "Privilege": "VVIP"
  },
  "llMr․Wizardll": {
    "Rank": "Management",
    "Privilege": "Staff"
  },
  "LaxxusZ": {
    "Rank": "Management",
    "Privilege": "Staff"
  },
  "Hotoroti": {
    "Rank": "Booster",
    "Privilege": "VVIP"
  },
  "BazzVR": {
    "Rank": "Booster",
    "Privilege": "VVIP"
  },
  "Sminky Grandpa": {
    "Rank": "Management",
    "Privilege": "Staff"
  },
  "࿙༒Y A M I༒࿚": {
    "Rank": "Patreon",
    "Privilege": "VVIP"
  },
  "N0mar": {
    "Rank": "Booster",
    "Privilege": "VVIP"
  },
  "Buster Skull": {
    "Rank": "Booster",
    "Privilege": "VVIP"
  },
  "MoopMoop": {
    "Rank": "Booster",
    "Privilege": "VVIP"
  },
  "Sakura~Alpaca27": {
    "Rank": "DancerTrial",
    "Privilege": "Staff"
  },
  "PlundaDownUnda": {
    "Rank": "Booster",
    "Privilege": "VVIP"
  },
  "AlulaNova": {
    "Rank": "Booster",
    "Privilege": "VVIP"
  },
  "｜Megu｜": {
    "Rank": "Patreon",
    "Privilege": "VVIP"
  },
  "Lillysky": {
    "Rank": "Booster",
    "Privilege": "VVIP"
  },
  "6SARGE9": {
    "Rank": "Booster",
    "Privilege": "VVIP"
  }
}